vsutillib/process/__init__.py
vsutillib/process/utils.py
vsutillib/process/classes/__init__.py
vsutillib/process/classes/multiprocessing.py
vsutillib/process/classes/multithreading.py
vsutillib/process/classes/runcommand.py
vsutillib_process-1.6.0.dist-info/AUTHORS
vsutillib_process-1.6.0.dist-info/LICENSE.txt
vsutillib_process-1.6.0.dist-info/METADATA
vsutillib_process-1.6.0.dist-info/WHEEL
vsutillib_process-1.6.0.dist-info/top_level.txt
vsutillib_process-1.6.0.dist-info/RECORD
